hasattr_safe/__init__.py
hasattr_safe/hasattr_safe.py
hasattr_safe-0.1.1.dist-info/DESCRIPTION.rst
hasattr_safe-0.1.1.dist-info/METADATA
hasattr_safe-0.1.1.dist-info/metadata.json
hasattr_safe-0.1.1.dist-info/RECORD
hasattr_safe-0.1.1.dist-info/top_level.txt
hasattr_safe-0.1.1.dist-info/WHEEL
