Metadata-Version: 2.0
Name: hasattr-safe
Version: 0.1.1
Summary: A non-harmful hasattr
Home-page: UNKNOWN
Author: Richard O'Dwyer
Author-email: richard@richard.do
License: Creative Commons Attribution-Noncommercial-Share Alike license
Platform: UNKNOWN
Classifier: Intended Audience :: Developers
Classifier: Operating System :: OS Independent
Classifier: Programming Language :: Python
Classifier: Programming Language :: Python :: 2
Classifier: Programming Language :: Python :: 2.7
Classifier: Programming Language :: Python :: 3
Classifier: Programming Language :: Python :: 3.3
Classifier: Programming Language :: Python :: 3.4
Classifier: Programming Language :: Python :: 3.5
Classifier: Topic :: Internet :: WWW/HTTP
Requires-Dist: wheel
Requires-Dist: six
